<?xml version="1.0" encoding="UTF-8"?>
<sbe:messageSchema xmlns:sbe="http://fixprotocol.io/2016/sbe"
                   package="booksnap" id="8" schemaId="8" version="1"
                   byteOrder="littleEndian">
  <types>
    <composite name="messageHeader">
      <type name="blockLength" primitiveType="uint16"/>
      <type name="templateId"  primitiveType="uint16"/>
      <type name="schemaId"    primitiveType="uint16"/>
      <type name="version"     primitiveType="uint16"/>
    </composite>
    <composite name="groupSizeEncoding">
      <type name="blockLength" primitiveType="uint16"/>
      <type name="numInGroup"  primitiveType="uint16"/>
    </composite>
    <enum name="Side" encodingType="uint8">
      <validValue name="BID">0</validValue>
      <validValue name="ASK">1</validValue>
    </enum>
  </types>

  <sbe:message name="BookSnapshot" id="1">
    <field name="priceMin" id="1" type="int64"/>
    <field name="tickSize" id="2" type="int64"/>
    <field name="nLevels"  id="3" type="uint32"/>
    <field name="capacity" id="4" type="uint32"/>
    <field name="hwm"      id="5" type="uint32"/>
    <field name="bestBid"  id="6" type="int32"/>
    <field name="bestAsk"  id="7" type="int32"/>

    <group name="levels" id="10" dimensionType="groupSizeEncoding">
      <field name="side"      id="11" type="Side"/>
      <field name="levelTick" id="12" type="uint32"/>
      <field name="qtyTotal"  id="13" type="int64"/>
      <field name="count"     id="14" type="uint32"/>
      <field name="head"      id="15" type="uint32"/>
      <field name="tail"      id="16" type="uint32"/>
    </group>

    <group name="orders" id="20" dimensionType="groupSizeEncoding">
      <field name="slot"    id="21" type="uint32"/>
      <field name="orderId" id="22" type="int64"/>
      <field name="price"   id="23" type="int64"/>
      <field name="qty"     id="24" type="int64"/>
      <field name="filled"  id="25" type="int64"/>
      <field name="side"    id="26" type="Side"/>
      <field name="next"    id="27" type="uint32"/>
      <field name="prev"    id="28" type="uint32"/>
    </group>
  </sbe:message>
</sbe:messageSchema>
